pyppeteer_fork/__init__.py
pyppeteer_fork/browser.py
pyppeteer_fork/chromium_downloader.py
pyppeteer_fork/command.py
pyppeteer_fork/connection.py
pyppeteer_fork/coverage.py
pyppeteer_fork/dialog.py
pyppeteer_fork/element_handle.py
pyppeteer_fork/emulation_manager.py
pyppeteer_fork/errors.py
pyppeteer_fork/execution_context.py
pyppeteer_fork/frame_manager.py
pyppeteer_fork/helper.py
pyppeteer_fork/input.py
pyppeteer_fork/launcher.py
pyppeteer_fork/multimap.py
pyppeteer_fork/navigator_watcher.py
pyppeteer_fork/network_manager.py
pyppeteer_fork/options.py
pyppeteer_fork/page.py
pyppeteer_fork/target.py
pyppeteer_fork/tracing.py
pyppeteer_fork/us_keyboard_layout.py
pyppeteer_fork/util.py
pyppeteer_fork/worker.py
pyppeteer_fork-0.0.28.dist-info/LICENSE
pyppeteer_fork-0.0.28.dist-info/METADATA
pyppeteer_fork-0.0.28.dist-info/WHEEL
pyppeteer_fork-0.0.28.dist-info/entry_points.txt
pyppeteer_fork-0.0.28.dist-info/top_level.txt
pyppeteer_fork-0.0.28.dist-info/RECORD
