Metadata-Version: 2.1
Name: pyppeteer-fork
Version: 0.0.28
Summary: Headless chrome/chromium automation library (unofficial port of puppeteer)
Home-page: https://github.com/miyakogi/pyppeteer_fork
Author: Hiroyuki Takagi
Author-email: miyako.dev@gmail.com
License: MIT license
Keywords: pyppeteer_fork
Platform: UNKNOWN
Classifier: Development Status :: 3 - Alpha
Classifier: Intended Audience :: Developers
Classifier: License :: OSI Approved :: MIT License
Classifier: Natural Language :: English
Classifier: Programming Language :: Python :: 3
Classifier: Programming Language :: Python :: 3.5
Classifier: Programming Language :: Python :: 3.6
Classifier: Programming Language :: Python :: 3.7
Requires-Python: >=3.5
Requires-Dist: pyee (<6)
Requires-Dist: websockets (>=7.0)
Requires-Dist: appdirs
Requires-Dist: urllib3 (<1.25)
Requires-Dist: tqdm
